LICENSE
README.md
setup.cfg
setup.py
pulp_utils/__init__.py
pulp_utils/report.py
pulp_utils/transportation.py
pulp_utils/tsp.py
pulp_utils.egg-info/PKG-INFO
pulp_utils.egg-info/SOURCES.txt
pulp_utils.egg-info/dependency_links.txt
pulp_utils.egg-info/requires.txt
pulp_utils.egg-info/top_level.txt